myqq/__init__.py
myqq/send.py
myqq-0.0.6.dist-info/LICENSE
myqq-0.0.6.dist-info/METADATA
myqq-0.0.6.dist-info/WHEEL
myqq-0.0.6.dist-info/top_level.txt
myqq-0.0.6.dist-info/RECORD
